filenoti/filenoti.py
filenoti-0.0.5.dist-info/METADATA
filenoti-0.0.5.dist-info/WHEEL
filenoti-0.0.5.dist-info/top_level.txt
filenoti-0.0.5.dist-info/RECORD
